.coveragerc
.readthedocs.yml
CHANGELOG.md
LICENSE
MANIFEST.in
README.md
pyproject.toml
setup.py
docs/.gitignore
docs/Makefile
docs/api.rst
docs/conf.py
docs/index.rst
docs/installation.rst
docs/make.bat
docs/specification.rst
docs/_static/copybutton.js
docs/_templates/layout.html
docs/api/wwt_kernel_data_relay.load_jupyter_server_extension.rst
docs/api/wwt_kernel_data_relay.serverextension.load_jupyter_server_extension.rst
docs/images/logo.png
jupyter-config/nb-config/wwt_kernel_data_relay.json
jupyter-config/server-config/wwt_kernel_data_relay.json
wwt_kernel_data_relay/__init__.py
wwt_kernel_data_relay/serverextension.py
wwt_kernel_data_relay.egg-info/PKG-INFO
wwt_kernel_data_relay.egg-info/SOURCES.txt
wwt_kernel_data_relay.egg-info/dependency_links.txt
wwt_kernel_data_relay.egg-info/requires.txt
wwt_kernel_data_relay.egg-info/top_level.txt