Metadata-Version: 2.1
Name: wwt-kernel-data-relay
Version: 0.3.0
Summary: Jupyter server extension to allow kernels to make data web-accessible
Home-page: https://github.com/WorldWideTelescope/wwt_kernel_data_relay/
Author: WorldWide Telescope Team
Author-email: hello@worldwidetelescope.org
License: MIT
Platform: Linux
Platform: Mac OS X
Platform: Windows
Classifier: Intended Audience :: Science/Research
Classifier: License :: OSI Approved :: MIT License
Classifier: Operating System :: OS Independent
Classifier: Programming Language :: Python :: 3.7
Classifier: Programming Language :: Python :: 3.8
Classifier: Programming Language :: Python :: 3.9
Classifier: Topic :: Scientific/Engineering :: Astronomy
Classifier: Topic :: Scientific/Engineering :: Visualization
Provides-Extra: test
Provides-Extra: docs
License-File: LICENSE
